dynamic_forms/__init__.py
django_forms_dynamic-1.0.0.dist-info/LICENSE
django_forms_dynamic-1.0.0.dist-info/METADATA
django_forms_dynamic-1.0.0.dist-info/WHEEL
django_forms_dynamic-1.0.0.dist-info/top_level.txt
django_forms_dynamic-1.0.0.dist-info/RECORD
