Metadata-Version: 2.1
Name: django-forms-dynamic
Version: 1.0.0
Summary: Resolve form field arguments dynamically when a form is instantiated, not when it's declared.
Home-page: https://github.com/dabapps/django-forms-dynamic
Author: DabApps
Author-email: hello@dabapps.com
License: BSD
Project-URL: Changelog, https://github.com/dabapps/django-forms-dynamic/releases
Project-URL: Issues, https://github.com/dabapps/django-forms-dynamic/issues
Platform: UNKNOWN
Requires-Python: >=3.6
